vcml.py
vcml-0.0.1.dist-info/LICENSE
vcml-0.0.1.dist-info/METADATA
vcml-0.0.1.dist-info/WHEEL
vcml-0.0.1.dist-info/top_level.txt
vcml-0.0.1.dist-info/RECORD
