Metadata-Version: 2.1
Name: vcml
Version: 0.0.1
Summary: machine learning
Author: aiml department
Author-email: aiml6thsem@gmail.com
License: MIT
Keywords: machine learning lab,mllab
Classifier: Programming Language :: Python :: 3
Classifier: License :: OSI Approved :: MIT License
Classifier: Operating System :: OS Independent
Requires-Python: >=3.7
License-File: LICENSE
